README.md
setup.cfg
setup.py
kkz/Binomialdistribution.py
kkz/Gaussiandistribution.py
kkz/Generaldistribution.py
kkz/__init__.py
kkz.egg-info/PKG-INFO
kkz.egg-info/SOURCES.txt
kkz.egg-info/dependency_links.txt
kkz.egg-info/not-zip-safe
kkz.egg-info/top_level.txt